{
    "_values": {
        "career": null,
        "civil_status": "Married",
        "committees": [
            "Backbencher Committee",
            "Ministerial Consultative Committee on Ports & Shipping",
            "Ministerial Consultative Committee on Development Co-ordination and Monitoring"
        ],
        "dob": "15-04-1979",
        "electoral": "Digamadulla",
        "name": "Hon. D. Weerasingha, M.P.",
        "occupation": "",
        "party": "Sri Lanka Podujana Peramuna (SLPP)",
        "portfolio": "",
        "religion": "Buddhism"
    }
}