{"career": null, "civil_status": "විවාහකයි", "committees": ["ගෘහ කමිටුව", "අධ්‍යාපන අමාත්‍ය උපදේශක කාරක සභාව", "පාර්ලිමේන්තුවේ කාන්තා පාර්ලිමේන්තු මන්ත්‍රී මණ්ඩලය", "ශ්‍රී ලංකාවේ ස්ත්‍රී පුරුෂ සමාජභාවය මත පදනම් වූ වෙනස්කම් කිරීම් සහ කාන්තා අයිතීන් උල්ලංඝනය කිරීම් පිළිබඳව විශේෂ අවධානයක් යොමු කරමින් ස්ත්‍රී පුරුෂ සමානාත්මතාවය සහ සමානාත්මතාවය සහතික කිරීම සඳහා එහි නිර්දේශ සොයා බලා පාර්ලිමේන්තුවට වාර්තා කිරීමට පාර්ලිමේන්තු තේරීම් කාරක සභාව"], "dob": "11-09-1974", "electoral": "ජාතික ලැයිස්තුව", "name": "ගරු. (ආචාර්ය) (මිය) සීතා අරඹේපොල, එම්.පී.", "occupation": "", "party": "ශ්‍රී ලංකා පොදුජන පෙරමුණ (SLPP)", "portfolio": "නිපුණතා සංවර්ධන, වෘත්තීය අධ්‍යාපන, පර්යේෂණ සහ නවෝත්පාදන රාජ්‍ය අමාත්‍ය", "religion": "බුද්ධාගම"}